streamsx/geospatial/__init__.py
streamsx/geospatial/_geospatial.py
streamsx/geospatial/schema.py
streamsx.geospatial-1.1.4.dist-info/LICENSE.txt
streamsx.geospatial-1.1.4.dist-info/METADATA
streamsx.geospatial-1.1.4.dist-info/WHEEL
streamsx.geospatial-1.1.4.dist-info/top_level.txt
streamsx.geospatial-1.1.4.dist-info/RECORD
